pycoparsec/__about__.py
pycoparsec/__init__.py
pycoparsec/parser.py
pycoparsec-0.0.2.dist-info/METADATA
pycoparsec-0.0.2.dist-info/WHEEL
pycoparsec-0.0.2.dist-info/licenses/LICENSE.txt
pycoparsec-0.0.2.dist-info/RECORD
