Metadata-Version: 2.1
Name: pycoparsec
Version: 0.0.2
Summary: A proof-of-concept parser combinator library employing stack frame closures.
Project-URL: Documentation, https://github.com/DataKinds/pycoparsec#readme
Project-URL: Issues, https://github.com/DataKinds/pycoparsec/issues
Project-URL: Source, https://github.com/DataKinds/pycoparsec
Author-email: DataKinds <tslimkemann42@gmail.com>
License-Expression: LGPL-3.0-or-later
License-File: LICENSE.txt
Classifier: Development Status :: 2 - Pre-Alpha
Classifier: License :: OSI Approved :: GNU Lesser General Public License v3 or later (LGPLv3+)
Classifier: Programming Language :: Python
Classifier: Programming Language :: Python :: 3.8
Classifier: Programming Language :: Python :: 3.9
Classifier: Programming Language :: Python :: 3.10
Classifier: Programming Language :: Python :: 3.11
Classifier: Programming Language :: Python :: Implementation :: CPython
Classifier: Programming Language :: Python :: Implementation :: PyPy
Classifier: Topic :: Text Processing
Requires-Python: >=3.8
